torchmtl/__init__.py
torchmtl/model_builder.py
torchmtl/wrapping_layers.py
torchmtl-0.1.9.dist-info/LICENSE
torchmtl-0.1.9.dist-info/METADATA
torchmtl-0.1.9.dist-info/WHEEL
torchmtl-0.1.9.dist-info/RECORD
