Metadata-Version: 2.1
Name: torchmtl
Version: 0.1.9
Summary: A lightweight module for Multi-Task Learning in pytorch
License: MIT
Author: Christian Bock
Author-email: christian.bock@bsse.ethz.ch
Requires-Python: >=3.7,<4.0
Classifier: License :: OSI Approved :: MIT License
Classifier: Programming Language :: Python :: 3
Classifier: Programming Language :: Python :: 3.7
Classifier: Programming Language :: Python :: 3.8
Classifier: Programming Language :: Python :: 3.9
Classifier: Programming Language :: Python :: 3.10
Classifier: Programming Language :: Python :: 3.11
Requires-Dist: matplotlib (>=3.3.2,<4.0.0)
Requires-Dist: networkx (>=2.5,<3.0)
Requires-Dist: scipy (>=1.5.3,<2.0.0)
Requires-Dist: torch (>=1.6.0)
